{
	"info": {
		"_postman_id": "a0e91b60-e10c-4802-9c4c-b33b51023e6e",
		"name": "kata-sweet-shop",
		"schema": "https://schema.getpostman.com/json/collection/v2.1.0/collection.json",
		"_exporter_id": "44000008",
		"_collection_link": "https://dmeel-9706862.postman.co/workspace/Dmeel's-Workspace~04870ad2-f541-4b4b-891b-078f5fb17a05/collection/44000008-a0e91b60-e10c-4802-9c4c-b33b51023e6e?action=share&source=collection_link&creator=44000008"
	},
	"item": [
		{
			"name": "Auth",
			"item": [
				{
					"name": "Register",
					"request": {
						"method": "POST",
						"header": [
							{
								"key": "Content-Type",
								"value": "application/json"
							}
						],
						"body": {
							"mode": "raw",
							"raw": "{\r\n    \"name\": \"John Doe\",\r\n    \"email\": \"john@example.com\",\r\n    \"password\": \"Password123!\"\r\n}",
							"options": {
								"raw": {
									"language": "json"
								}
							}
						},
						"url": {
							"raw": "{{baseUrl}}/api/auth/register",
							"host": [
								"{{baseUrl}}"
							],
							"path": [
								"api",
								"auth",
								"register"
							]
						}
					},
					"response": []
				},
				{
					"name": "Login",
					"request": {
						"method": "POST",
						"header": [
							{
								"key": "Content-Type",
								"value": "application/json"
							}
						],
						"body": {
							"mode": "raw",
							"raw": "{\r\n    \"email\": \"john@example.com\",\r\n    \"password\": \"Password123!\"\r\n}",
							"options": {
								"raw": {
									"language": "json"
								}
							}
						},
						"url": {
							"raw": "{{baseUrl}}/api/auth/login",
							"host": [
								"{{baseUrl}}"
							],
							"path": [
								"api",
								"auth",
								"login"
							]
						}
					},
					"response": []
				},
				{
					"name": "Get Current User",
					"request": {
						"auth": {
							"type": "bearer",
							"bearer": [
								{
									"key": "token",
									"value": "",
									"type": "string"
								}
							]
						},
						"method": "GET",
						"header": [],
						"url": {
							"raw": "{{baseUrl}}/api/auth/me",
							"host": [
								"{{baseUrl}}"
							],
							"path": [
								"api",
								"auth",
								"me"
							]
						}
					},
					"response": []
				}
			]
		},
		{
			"name": "Categories",
			"item": [
				{
					"name": "List Categories",
					"request": {
						"method": "GET",
						"header": [],
						"url": {
							"raw": "{{baseUrl}}/api/sweet/category?page=1&limit=20",
							"host": [
								"{{baseUrl}}"
							],
							"path": [
								"api",
								"sweet",
								"category"
							],
							"query": [
								{
									"key": "page",
									"value": "1"
								},
								{
									"key": "limit",
									"value": "20"
								}
							]
						}
					},
					"response": []
				},
				{
					"name": "Get Category by ID",
					"request": {
						"method": "GET",
						"header": [],
						"url": {
							"raw": "{{baseUrl}}/api/sweet/category/1",
							"host": [
								"{{baseUrl}}"
							],
							"path": [
								"api",
								"sweet",
								"category",
								"1"
							]
						}
					},
					"response": []
				},
				{
					"name": "Get Active Categories",
					"request": {
						"method": "GET",
						"header": [],
						"url": {
							"raw": "{{baseUrl}}/api/sweet/category/active/list",
							"host": [
								"{{baseUrl}}"
							],
							"path": [
								"api",
								"sweet",
								"category",
								"active",
								"list"
							]
						}
					},
					"response": []
				},
				{
					"name": "Create Category (Admin)",
					"request": {
						"auth": {
							"type": "bearer",
							"bearer": [
								{
									"key": "token",
									"value": "",
									"type": "string"
								}
							]
						},
						"method": "POST",
						"header": [
							{
								"key": "Content-Type",
								"value": "application/json"
							}
						],
						"body": {
							"mode": "raw",
							"raw": "{\r\n    \"name\": \"Chocolates\"\r\n}",
							"options": {
								"raw": {
									"language": "json"
								}
							}
						},
						"url": {
							"raw": "{{baseUrl}}/api/sweet/category",
							"host": [
								"{{baseUrl}}"
							],
							"path": [
								"api",
								"sweet",
								"category"
							]
						}
					},
					"response": []
				},
				{
					"name": "Update Category (Admin)",
					"request": {
						"auth": {
							"type": "bearer",
							"bearer": [
								{
									"key": "token",
									"value": "",
									"type": "string"
								}
							]
						},
						"method": "PUT",
						"header": [
							{
								"key": "Content-Type",
								"value": "application/json"
							}
						],
						"body": {
							"mode": "raw",
							"raw": "{\r\n    \"name\": \"Updated Chocolates\"\r\n}",
							"options": {
								"raw": {
									"language": "json"
								}
							}
						},
						"url": {
							"raw": "{{baseUrl}}/api/sweet/category/1",
							"host": [
								"{{baseUrl}}"
							],
							"path": [
								"api",
								"sweet",
								"category",
								"1"
							]
						}
					},
					"response": []
				},
				{
					"name": "Delete Category (Admin)",
					"request": {
						"auth": {
							"type": "bearer",
							"bearer": [
								{
									"key": "token",
									"value": "",
									"type": "string"
								}
							]
						},
						"method": "DELETE",
						"header": [],
						"url": {
							"raw": "{{baseUrl}}/api/sweet/category/1",
							"host": [
								"{{baseUrl}}"
							],
							"path": [
								"api",
								"sweet",
								"category",
								"1"
							]
						}
					},
					"response": []
				},
				{
					"name": "Reactivate Category (Admin)",
					"request": {
						"auth": {
							"type": "bearer",
							"bearer": [
								{
									"key": "token",
									"value": "",
									"type": "string"
								}
							]
						},
						"method": "POST",
						"header": [],
						"url": {
							"raw": "{{baseUrl}}/api/sweet/category/1/reactivate",
							"host": [
								"{{baseUrl}}"
							],
							"path": [
								"api",
								"sweet",
								"category",
								"1",
								"reactivate"
							]
						}
					},
					"response": []
				}
			]
		},
		{
			"name": "Sweets",
			"item": [
				{
					"name": "List Sweets",
					"request": {
						"auth": {
							"type": "bearer",
							"bearer": [
								{
									"key": "token",
									"value": "",
									"type": "string"
								}
							]
						},
						"method": "GET",
						"header": [],
						"url": {
							"raw": "{{baseUrl}}/api/sweets?page=1&limit=20",
							"host": [
								"{{baseUrl}}"
							],
							"path": [
								"api",
								"sweets"
							],
							"query": [
								{
									"key": "page",
									"value": "1"
								},
								{
									"key": "limit",
									"value": "20"
								}
							]
						}
					},
					"response": []
				},
				{
					"name": "Search Sweets",
					"request": {
						"auth": {
							"type": "bearer",
							"bearer": [
								{
									"key": "token",
									"value": "",
									"type": "string"
								}
							]
						},
						"method": "GET",
						"header": [],
						"url": {
							"raw": "{{baseUrl}}/api/sweets/search?q=chocolate&category=1&minPrice=1&maxPrice=10",
							"host": [
								"{{baseUrl}}"
							],
							"path": [
								"api",
								"sweets",
								"search"
							],
							"query": [
								{
									"key": "q",
									"value": "chocolate"
								},
								{
									"key": "category",
									"value": "1"
								},
								{
									"key": "minPrice",
									"value": "1"
								},
								{
									"key": "maxPrice",
									"value": "10"
								}
							]
						}
					},
					"response": []
				},
				{
					"name": "Create Sweet (Admin)",
					"request": {
						"auth": {
							"type": "bearer",
							"bearer": [
								{
									"key": "token",
									"value": "",
									"type": "string"
								}
							]
						},
						"method": "POST",
						"header": [
							{
								"key": "Content-Type",
								"value": "application/json"
							}
						],
						"body": {
							"mode": "raw",
							"raw": "{\r\n    \"name\": \"Dark Chocolate Bar\",\r\n    \"categoryId\": 1,\r\n    \"price\": 2.50,\r\n    \"quantity\": 100\r\n}",
							"options": {
								"raw": {
									"language": "json"
								}
							}
						},
						"url": {
							"raw": "{{baseUrl}}/api/sweets",
							"host": [
								"{{baseUrl}}"
							],
							"path": [
								"api",
								"sweets"
							]
						}
					},
					"response": []
				},
				{
					"name": "Update Sweet (Admin)",
					"request": {
						"auth": {
							"type": "bearer",
							"bearer": [
								{
									"key": "token",
									"value": "",
									"type": "string"
								}
							]
						},
						"method": "PUT",
						"header": [
							{
								"key": "Content-Type",
								"value": "application/json"
							}
						],
						"body": {
							"mode": "raw",
							"raw": "{\r\n    \"name\": \"Premium Dark Chocolate Bar\",\r\n    \"price\": 3.00\r\n}",
							"options": {
								"raw": {
									"language": "json"
								}
							}
						},
						"url": {
							"raw": "{{baseUrl}}/api/sweets/1",
							"host": [
								"{{baseUrl}}"
							],
							"path": [
								"api",
								"sweets",
								"1"
							]
						}
					},
					"response": []
				},
				{
					"name": "Delete Sweet (Admin)",
					"request": {
						"auth": {
							"type": "bearer",
							"bearer": [
								{
									"key": "token",
									"value": "",
									"type": "string"
								}
							]
						},
						"method": "DELETE",
						"header": [],
						"url": {
							"raw": "{{baseUrl}}/api/sweets/1",
							"host": [
								"{{baseUrl}}"
							],
							"path": [
								"api",
								"sweets",
								"1"
							]
						}
					},
					"response": []
				},
				{
					"name": "Reactivate Sweet (Admin)",
					"request": {
						"auth": {
							"type": "bearer",
							"bearer": [
								{
									"key": "token",
									"value": "",
									"type": "string"
								}
							]
						},
						"method": "POST",
						"header": [],
						"url": {
							"raw": "{{baseUrl}}/api/sweets/1/reactivate",
							"host": [
								"{{baseUrl}}"
							],
							"path": [
								"api",
								"sweets",
								"1",
								"reactivate"
							]
						}
					},
					"response": []
				},
				{
					"name": "Purchase Sweet",
					"request": {
						"auth": {
							"type": "bearer",
							"bearer": [
								{
									"key": "token",
									"value": "",
									"type": "string"
								}
							]
						},
						"method": "POST",
						"header": [
							{
								"key": "Content-Type",
								"value": "application/json"
							}
						],
						"body": {
							"mode": "raw",
							"raw": "{\r\n    \"quantity\": 5\r\n}",
							"options": {
								"raw": {
									"language": "json"
								}
							}
						},
						"url": {
							"raw": "{{baseUrl}}/api/sweets/1/purchase",
							"host": [
								"{{baseUrl}}"
							],
							"path": [
								"api",
								"sweets",
								"1",
								"purchase"
							]
						}
					},
					"response": []
				},
				{
					"name": "Restock Sweet (Admin)",
					"request": {
						"auth": {
							"type": "bearer",
							"bearer": [
								{
									"key": "token",
									"value": "",
									"type": "string"
								}
							]
						},
						"method": "POST",
						"header": [
							{
								"key": "Content-Type",
								"value": "application/json"
							}
						],
						"body": {
							"mode": "raw",
							"raw": "{\r\n    \"quantity\": 50\r\n}",
							"options": {
								"raw": {
									"language": "json"
								}
							}
						},
						"url": {
							"raw": "{{baseUrl}}/api/sweets/1/restock",
							"host": [
								"{{baseUrl}}"
							],
							"path": [
								"api",
								"sweets",
								"1",
								"restock"
							]
						}
					},
					"response": []
				}
			]
		},
		{
			"name": "Purchases",
			"item": [
				{
					"name": "Create Purchase",
					"request": {
						"auth": {
							"type": "bearer",
							"bearer": [
								{
									"key": "token",
									"value": "",
									"type": "string"
								}
							]
						},
						"method": "POST",
						"header": [
							{
								"key": "Content-Type",
								"value": "application/json"
							}
						],
						"body": {
							"mode": "raw",
							"raw": "{\r\n    \"sweetId\": 1,\r\n    \"quantity\": 3\r\n}",
							"options": {
								"raw": {
									"language": "json"
								}
							}
						},
						"url": {
							"raw": "{{baseUrl}}/api/purchases",
							"host": [
								"{{baseUrl}}"
							],
							"path": [
								"api",
								"purchases"
							]
						}
					},
					"response": []
				},
				{
					"name": "List Purchases",
					"request": {
						"auth": {
							"type": "bearer",
							"bearer": [
								{
									"key": "token",
									"value": "",
									"type": "string"
								}
							]
						},
						"method": "GET",
						"header": [],
						"url": {
							"raw": "{{baseUrl}}/api/purchases?page=1&limit=20",
							"host": [
								"{{baseUrl}}"
							],
							"path": [
								"api",
								"purchases"
							],
							"query": [
								{
									"key": "page",
									"value": "1"
								},
								{
									"key": "limit",
									"value": "20"
								}
							]
						}
					},
					"response": []
				},
				{
					"name": "Get Purchase by ID",
					"request": {
						"auth": {
							"type": "bearer",
							"bearer": [
								{
									"key": "token",
									"value": "",
									"type": "string"
								}
							]
						},
						"method": "GET",
						"header": [],
						"url": {
							"raw": "{{baseUrl}}/api/purchases/1",
							"host": [
								"{{baseUrl}}"
							],
							"path": [
								"api",
								"purchases",
								"1"
							]
						}
					},
					"response": []
				},
				{
					"name": "Get Purchases by User",
					"request": {
						"auth": {
							"type": "bearer",
							"bearer": [
								{
									"key": "token",
									"value": "",
									"type": "string"
								}
							]
						},
						"method": "GET",
						"header": [],
						"url": {
							"raw": "{{baseUrl}}/api/purchases/user/1?page=1&limit=20",
							"host": [
								"{{baseUrl}}"
							],
							"path": [
								"api",
								"purchases",
								"user",
								"1"
							],
							"query": [
								{
									"key": "page",
									"value": "1"
								},
								{
									"key": "limit",
									"value": "20"
								}
							]
						}
					},
					"response": []
				},
				{
					"name": "Get Purchases by Sweet (Admin)",
					"request": {
						"auth": {
							"type": "bearer",
							"bearer": [
								{
									"key": "token",
									"value": "",
									"type": "string"
								}
							]
						},
						"method": "GET",
						"header": [],
						"url": {
							"raw": "{{baseUrl}}/api/purchases/sweet/1?page=1&limit=20",
							"host": [
								"{{baseUrl}}"
							],
							"path": [
								"api",
								"purchases",
								"sweet",
								"1"
							],
							"query": [
								{
									"key": "page",
									"value": "1"
								},
								{
									"key": "limit",
									"value": "20"
								}
							]
						}
					},
					"response": []
				}
			]
		}
	],
	"variable": [
		{
			"key": "baseUrl",
			"value": "http://localhost:3000",
			"type": "string"
		}
	]
}